Surface_training_model/__init__.py
Surface_training_model/evaluate.py
Surface_training_model/hubconf.py
Surface_training_model/predict.py
Surface_training_model/train.py
Surface_training_model/unet/HRnet.py
Surface_training_model/unet/__init__.py
Surface_training_model/unet/channel_unet.py
Surface_training_model/unet/model.py
Surface_training_model/unet/unet_model.py
Surface_training_model/unet/unet_parts.py
Surface_training_model/utils/__init__.py
Surface_training_model/utils/data_loading.py
Surface_training_model/utils/dice_score.py
Surface_training_model/utils/utils.py
Surface_training_model-0.1.2.dist-info/LICENSE
Surface_training_model-0.1.2.dist-info/METADATA
Surface_training_model-0.1.2.dist-info/WHEEL
Surface_training_model-0.1.2.dist-info/top_level.txt
Surface_training_model-0.1.2.dist-info/RECORD
