Metadata-Version: 2.1
Name: Surface-training-model
Version: 0.1.2
Summary: SHARAD surface echo extraction model training package based on deep learning
Author: Dongfang Fan
Author-email: 2300541001@email.szu.edu.cn
Classifier: Programming Language :: Python :: 3
Classifier: License :: OSI Approved :: MIT License
Classifier: Operating System :: OS Independent
Requires-Python: >=3.6
License-File: LICENSE
Requires-Dist: numpy
